odoo/addons/ssi_hr_payroll/README.rst
odoo/addons/ssi_hr_payroll/__init__.py
odoo/addons/ssi_hr_payroll/__manifest__.py
odoo/addons/ssi_hr_payroll/menu.xml
odoo/addons/ssi_hr_payroll/data/approval_template_data.xml
odoo/addons/ssi_hr_payroll/data/ir_sequence_data.xml
odoo/addons/ssi_hr_payroll/data/policy_template_data.xml
odoo/addons/ssi_hr_payroll/data/sequence_template_data.xml
odoo/addons/ssi_hr_payroll/demo/account_account_demo.xml
odoo/addons/ssi_hr_payroll/demo/account_journal_demo.xml
odoo/addons/ssi_hr_payroll/demo/hr_employee_input_type_demo.xml
odoo/addons/ssi_hr_payroll/demo/hr_payslip_input_type_demo.xml
odoo/addons/ssi_hr_payroll/demo/hr_payslip_type_demo.xml
odoo/addons/ssi_hr_payroll/demo/hr_salary_contribution_demo.xml
odoo/addons/ssi_hr_payroll/demo/hr_salary_rule_category_demo.xml
odoo/addons/ssi_hr_payroll/demo/hr_salary_rule_demo.xml
odoo/addons/ssi_hr_payroll/demo/hr_salary_structure_demo.xml
odoo/addons/ssi_hr_payroll/models/__init__.py
odoo/addons/ssi_hr_payroll/models/hr_employee.py
odoo/addons/ssi_hr_payroll/models/hr_employee_input.py
odoo/addons/ssi_hr_payroll/models/hr_employee_input_type.py
odoo/addons/ssi_hr_payroll/models/hr_payslip.py
odoo/addons/ssi_hr_payroll/models/hr_payslip_input.py
odoo/addons/ssi_hr_payroll/models/hr_payslip_input_type.py
odoo/addons/ssi_hr_payroll/models/hr_payslip_line.py
odoo/addons/ssi_hr_payroll/models/hr_payslip_type.py
odoo/addons/ssi_hr_payroll/models/hr_salary_contribution.py
odoo/addons/ssi_hr_payroll/models/hr_salary_rule.py
odoo/addons/ssi_hr_payroll/models/hr_salary_rule_category.py
odoo/addons/ssi_hr_payroll/models/hr_salary_structure.py
odoo/addons/ssi_hr_payroll/security/ir.model.access.csv
odoo/addons/ssi_hr_payroll/security/ir_module_category_data.xml
odoo/addons/ssi_hr_payroll/security/ir_rule_data.xml
odoo/addons/ssi_hr_payroll/security/res_group_data.xml
odoo/addons/ssi_hr_payroll/static/description/icon.png
odoo/addons/ssi_hr_payroll/views/hr_employee_input_type_views.xml
odoo14_addon_ssi_hr_payroll-14.0.2.2.0.dist-info/METADATA
odoo14_addon_ssi_hr_payroll-14.0.2.2.0.dist-info/WHEEL
odoo14_addon_ssi_hr_payroll-14.0.2.2.0.dist-info/top_level.txt
odoo14_addon_ssi_hr_payroll-14.0.2.2.0.dist-info/RECORD
